setup.cfg
setup.py
gemini/__init__.py
gemini/client.py
gemini/error.py
gemini_python_unoffc.egg-info/PKG-INFO
gemini_python_unoffc.egg-info/SOURCES.txt
gemini_python_unoffc.egg-info/dependency_links.txt
gemini_python_unoffc.egg-info/requires.txt
gemini_python_unoffc.egg-info/top_level.txt