Metadata-Version: 1.1
Name: gemini-python-unoffc
Version: 0.1
Summary: An Unofficial Python library for the Gemini Exchange REST API.
Home-page: https://github.com/mattselph/gemini-python-unoffc
Author: Matt Selph
Author-email: mattselph@outlook.com
License: MIT
Keywords: bitcoin ethereum api gemini
Platform: UNKNOWN
Classifier: Intended Audience :: Developers
Classifier: License :: OSI Approved :: MIT License
Classifier: Operating System :: OS Independent
Classifier: Programming Language :: Python :: 3
Classifier: Programming Language :: Python :: 3.2
Classifier: Programming Language :: Python :: 3.3
Classifier: Programming Language :: Python :: 3.4
Classifier: Programming Language :: Python :: 3.5
Classifier: Topic :: Software Development :: Libraries :: Python Modules
